[
  {
    "time": "12:00",
    "source": "market_rate",
    "BOC_EUR_mid": 818.3306,
    "BOC_EUR_buy": 815.4664,
    "BOC_EUR_sell": 821.1948,
    "BOC_USD_mid": 707.5639,
    "BOC_USD_buy": 706.1488,
    "BOC_USD_sell": 708.979,
    "BOC_JPY_mid": 4.5321,
    "BOC_JPY_buy": 4.514,
    "BOC_JPY_sell": 4.5502,
    "BOC_KRW_mid": 0.4814,
    "BOC_KRW_buy": 0.4742,
    "BOC_KRW_sell": 0.4886,
    "BOC_THB_mid": 21.9771,
    "BOC_THB_buy": 21.7573,
    "BOC_THB_sell": 22.1969,
    "ICBC_EUR_mid": 818.5761,
    "ICBC_EUR_buy": 815.7111,
    "ICBC_EUR_sell": 821.4411,
    "ICBC_USD_mid": 707.7054,
    "ICBC_USD_buy": 706.29,
    "ICBC_USD_sell": 709.1208,
    "ICBC_JPY_mid": 4.533,
    "ICBC_JPY_buy": 4.5149,
    "ICBC_JPY_sell": 4.5511,
    "ICBC_KRW_mid": 0.4818,
    "ICBC_KRW_buy": 0.4746,
    "ICBC_KRW_sell": 0.489,
    "ICBC_THB_mid": 21.9881,
    "ICBC_THB_buy": 21.7682,
    "ICBC_THB_sell": 22.208,
    "ABC_EUR_mid": 818.1669,
    "ABC_EUR_buy": 815.3033,
    "ABC_EUR_sell": 821.0305,
    "ABC_USD_mid": 707.4931,
    "ABC_USD_buy": 706.0781,
    "ABC_USD_sell": 708.9081,
    "ABC_JPY_mid": 4.5316,
    "ABC_JPY_buy": 4.5135,
    "ABC_JPY_sell": 4.5497,
    "ABC_KRW_mid": 0.4812,
    "ABC_KRW_buy": 0.474,
    "ABC_KRW_sell": 0.4884,
    "ABC_THB_mid": 21.9705,
    "ABC_THB_buy": 21.7508,
    "ABC_THB_sell": 22.1902
  }
]