[
  {
    "time": "12:00",
    "source": "market_rate",
    "BOC_EUR_mid": 809.52,
    "BOC_EUR_buy": 806.6867,
    "BOC_EUR_sell": 812.3533,
    "BOC_USD_mid": 686.9547,
    "BOC_USD_buy": 685.5808,
    "BOC_USD_sell": 688.3286,
    "BOC_JPY_mid": 4.3827,
    "BOC_JPY_buy": 4.3652,
    "BOC_JPY_sell": 4.4002,
    "BOC_KRW_mid": 0.4811,
    "BOC_KRW_buy": 0.4739,
    "BOC_KRW_sell": 0.4883,
    "BOC_THB_mid": 22.0921,
    "BOC_THB_buy": 21.8712,
    "BOC_THB_sell": 22.313,
    "ICBC_EUR_mid": 809.7629,
    "ICBC_EUR_buy": 806.9287,
    "ICBC_EUR_sell": 812.5971,
    "ICBC_USD_mid": 687.0921,
    "ICBC_USD_buy": 685.7179,
    "ICBC_USD_sell": 688.4663,
    "ICBC_JPY_mid": 4.3836,
    "ICBC_JPY_buy": 4.3661,
    "ICBC_JPY_sell": 4.4011,
    "ICBC_KRW_mid": 0.4815,
    "ICBC_KRW_buy": 0.4743,
    "ICBC_KRW_sell": 0.4887,
    "ICBC_THB_mid": 22.1031,
    "ICBC_THB_buy": 21.8821,
    "ICBC_THB_sell": 22.3241,
    "ABC_EUR_mid": 809.3581,
    "ABC_EUR_buy": 806.5253,
    "ABC_EUR_sell": 812.1909,
    "ABC_USD_mid": 686.886,
    "ABC_USD_buy": 685.5122,
    "ABC_USD_sell": 688.2598,
    "ABC_JPY_mid": 4.3823,
    "ABC_JPY_buy": 4.3648,
    "ABC_JPY_sell": 4.3998,
    "ABC_KRW_mid": 0.4809,
    "ABC_KRW_buy": 0.4737,
    "ABC_KRW_sell": 0.4881,
    "ABC_THB_mid": 22.0855,
    "ABC_THB_buy": 21.8646,
    "ABC_THB_sell": 22.3064
  }
]