[
  {
    "time": "12:00",
    "source": "market_rate",
    "BOC_EUR_mid": 809.9133,
    "BOC_EUR_buy": 807.0786,
    "BOC_EUR_sell": 812.748,
    "BOC_USD_mid": 696.3303,
    "BOC_USD_buy": 694.9376,
    "BOC_USD_sell": 697.723,
    "BOC_JPY_mid": 4.4092,
    "BOC_JPY_buy": 4.3916,
    "BOC_JPY_sell": 4.4268,
    "BOC_KRW_mid": 0.4727,
    "BOC_KRW_buy": 0.4656,
    "BOC_KRW_sell": 0.4798,
    "BOC_THB_mid": 22.2792,
    "BOC_THB_buy": 22.0564,
    "BOC_THB_sell": 22.502,
    "ICBC_EUR_mid": 810.1563,
    "ICBC_EUR_buy": 807.3208,
    "ICBC_EUR_sell": 812.9918,
    "ICBC_USD_mid": 696.4696,
    "ICBC_USD_buy": 695.0767,
    "ICBC_USD_sell": 697.8625,
    "ICBC_JPY_mid": 4.4101,
    "ICBC_JPY_buy": 4.3925,
    "ICBC_JPY_sell": 4.4277,
    "ICBC_KRW_mid": 0.4731,
    "ICBC_KRW_buy": 0.466,
    "ICBC_KRW_sell": 0.4802,
    "ICBC_THB_mid": 22.2903,
    "ICBC_THB_buy": 22.0674,
    "ICBC_THB_sell": 22.5132,
    "ABC_EUR_mid": 809.7513,
    "ABC_EUR_buy": 806.9172,
    "ABC_EUR_sell": 812.5854,
    "ABC_USD_mid": 696.2607,
    "ABC_USD_buy": 694.8682,
    "ABC_USD_sell": 697.6532,
    "ABC_JPY_mid": 4.4088,
    "ABC_JPY_buy": 4.3912,
    "ABC_JPY_sell": 4.4264,
    "ABC_KRW_mid": 0.4725,
    "ABC_KRW_buy": 0.4654,
    "ABC_KRW_sell": 0.4796,
    "ABC_THB_mid": 22.2725,
    "ABC_THB_buy": 22.0498,
    "ABC_THB_sell": 22.4952
  }
]